cli_weather/__init__.py
cli_weather/airquality_data.py
cli_weather/airquality_forecast_data.py
cli_weather/get_by_city.py
cli_weather/get_by_postalcode.py
cli_weather/main.py
cli_weather/weather_data.py
cli_weather/weather_forecast_data.py
cli_weather-0.1.5.dist-info/LICENSE
cli_weather-0.1.5.dist-info/METADATA
cli_weather-0.1.5.dist-info/WHEEL
cli_weather-0.1.5.dist-info/entry_points.txt
cli_weather-0.1.5.dist-info/top_level.txt
cli_weather-0.1.5.dist-info/RECORD
